gradelab50/__init__.py
gradelab50/main.py
gradelab50/templates/compraiz.jinja2
gradelab50/templates/default.jinja2
gradelab50-0.1.dist-info/LICENSE
gradelab50-0.1.dist-info/METADATA
gradelab50-0.1.dist-info/WHEEL
gradelab50-0.1.dist-info/entry_points.txt
gradelab50-0.1.dist-info/top_level.txt
gradelab50-0.1.dist-info/RECORD
