Metadata-Version: 2.1
Name: gradelab50
Version: 0.1
Summary: grade student submissions based on check50 json reports.
Home-page: https://github.com/computacaoraiz/gradelab50
Author: Abrantes Araújo Silva Filho
Author-email: abrantesasf@pm.me
Classifier: Programming Language :: Python :: 3
Classifier: License :: OSI Approved :: GNU General Public License v3 (GPLv3)
Classifier: Operating System :: OS Independent
Requires-Python: >=3.6
License-File: LICENSE
Requires-Dist: Jinja2 (>=2.10.1)
